qcengine/__init__.py
qcengine/__main__.py
qcengine/_version.py
qcengine/cli.py
qcengine/compute.py
qcengine/config.py
qcengine/exceptions.py
qcengine/extras.py
qcengine/mdi_server.py
qcengine/stock_mols.py
qcengine/testing.py
qcengine/units.py
qcengine/util.py
qcengine/procedures/__init__.py
qcengine/procedures/base.py
qcengine/procedures/berny.py
qcengine/procedures/geometric.py
qcengine/procedures/model.py
qcengine/procedures/optking.py
qcengine/procedures/qcmanybody.py
qcengine/procedures/torsiondrive.py
qcengine/procedures/nwchem_opt/__init__.py
qcengine/procedures/nwchem_opt/harvester.py
qcengine/programs/__init__.py
qcengine/programs/adcc.py
qcengine/programs/aimnet2.py
qcengine/programs/base.py
qcengine/programs/dftd3.py
qcengine/programs/dftd_ng.py
qcengine/programs/empirical_dispersion_resources.py
qcengine/programs/gcp.py
qcengine/programs/mace.py
qcengine/programs/model.py
qcengine/programs/molpro.py
qcengine/programs/mopac.py
qcengine/programs/mp2d.py
qcengine/programs/mrchem.py
qcengine/programs/openmm.py
qcengine/programs/psi4.py
qcengine/programs/qchem.py
qcengine/programs/qcore.py
qcengine/programs/qcvar_identities_resources.py
qcengine/programs/rdkit.py
qcengine/programs/terachem.py
qcengine/programs/terachem_frontend.py
qcengine/programs/terachem_pbs.py
qcengine/programs/torchani.py
qcengine/programs/xtb.py
qcengine/programs/cfour/__init__.py
qcengine/programs/cfour/germinate.py
qcengine/programs/cfour/harvester.py
qcengine/programs/cfour/keywords.py
qcengine/programs/cfour/runner.py
qcengine/programs/gamess/__init__.py
qcengine/programs/gamess/germinate.py
qcengine/programs/gamess/harvester.py
qcengine/programs/gamess/keywords.py
qcengine/programs/gamess/runner.py
qcengine/programs/nwchem/__init__.py
qcengine/programs/nwchem/errors.py
qcengine/programs/nwchem/germinate.py
qcengine/programs/nwchem/harvester.py
qcengine/programs/nwchem/keywords.py
qcengine/programs/nwchem/runner.py
qcengine/programs/tests/__init__.py
qcengine-0.34.0.dist-info/licenses/LICENSE
qcengine-0.34.0.dist-info/METADATA
qcengine-0.34.0.dist-info/WHEEL
qcengine-0.34.0.dist-info/entry_points.txt
qcengine-0.34.0.dist-info/top_level.txt
qcengine-0.34.0.dist-info/RECORD
