Metadata-Version: 2.4
Name: qcengine
Version: 0.34.0
Summary: A compute wrapper for Quantum Chemistry.
Home-page: https://github.com/MolSSI/QCEngine
Author: The QCArchive Development Team
Author-email: qcarchive@molssi.org
License: BSD-3C
Classifier: Development Status :: 4 - Beta
Classifier: Intended Audience :: Science/Research
Classifier: Programming Language :: Python :: 3 :: Only
Classifier: Programming Language :: Python :: 3
Classifier: Programming Language :: Python :: 3.7
Classifier: Programming Language :: Python :: 3.8
Classifier: Programming Language :: Python :: 3.9
Classifier: Programming Language :: Python :: 3.10
Classifier: Programming Language :: Python :: 3.11
Classifier: Programming Language :: Python :: 3.12
Classifier: Programming Language :: Python :: 3.13
Requires-Python: >=3.7.0,<3.14.0
License-File: LICENSE
Requires-Dist: pyyaml
Requires-Dist: py-cpuinfo
Requires-Dist: psutil
Requires-Dist: qcelemental<0.70.0,>=0.24.0
Requires-Dist: pydantic>=1.8.2
Requires-Dist: packaging
Provides-Extra: docs
Requires-Dist: sphinx==1.2.3; extra == "docs"
Requires-Dist: sphinxcontrib-napoleon; extra == "docs"
Requires-Dist: sphinx_rtd_theme; extra == "docs"
Requires-Dist: numpydoc; extra == "docs"
Provides-Extra: tests
Requires-Dist: pytest; extra == "tests"
Requires-Dist: pytest-cov; extra == "tests"
Provides-Extra: lint
Requires-Dist: black<23.0a0,>=22.1.0; extra == "lint"
Dynamic: author
Dynamic: author-email
Dynamic: classifier
Dynamic: description
Dynamic: description-content-type
Dynamic: home-page
Dynamic: license
Dynamic: license-file
Dynamic: provides-extra
Dynamic: requires-dist
Dynamic: requires-python
Dynamic: summary
